enc_cli-0.1.5.dist-info/licenses/LICENSE
enc_client/__init__.py
enc_client/cli.py
enc_client/enc.py
enc_client/session.py
enc_client/sshfs_handler.py
enc_cli-0.1.5.dist-info/METADATA
enc_cli-0.1.5.dist-info/WHEEL
enc_cli-0.1.5.dist-info/entry_points.txt
enc_cli-0.1.5.dist-info/top_level.txt
enc_cli-0.1.5.dist-info/RECORD
