Metadata-Version: 2.4
Name: enc-cli
Version: 0.1.5
Summary: Secure, Memory-Only Encryption for Code Execution
Author-email: Pranjal Bhaskare <pranjalab@gmail.com>
License: MIT
Classifier: Programming Language :: Python :: 3
Classifier: Operating System :: OS Independent
Requires-Python: >=3.9
License-File: LICENSE
Requires-Dist: click>=8.0
Requires-Dist: rich>=10.0
Requires-Dist: cryptography>=3.0
Requires-Dist: pexpect>=4.0
Dynamic: license-file
